azure_carbon_tracker/__init__.py
azure_carbon_tracker/azure_cost_management.py
azure_carbon_tracker/azure_retail_prices.py
azure_carbon_tracker/data/carbon_models.csv
azure_carbon_tracker/data/emission_factors.csv
azure_carbon_tracker/data/model_mapping.csv
azure_carbon_tracker/data/pricing.csv
azure_carbon_tracker-0.3.0.dist-info/METADATA
azure_carbon_tracker-0.3.0.dist-info/WHEEL
azure_carbon_tracker-0.3.0.dist-info/top_level.txt
azure_carbon_tracker-0.3.0.dist-info/RECORD
