Metadata-Version: 2.4
Name: azure-carbon-tracker
Version: 0.3.0
Summary: Azure carbon tracking via Cost Management API.
Author: Boris Ruf
Requires-Python: >=3.8
Requires-Dist: pandas
Requires-Dist: requests
Requires-Dist: azure-identity
Dynamic: requires-python
